SimpleModule/__init__.py
SimpleModule/add.py
SimpleModule/subtract.py
SimpleModule/extras/__init__.py
SimpleModule/extras/divide.py
SimpleModule/extras/multiply.py
example-pkg/__init__.py
example-pkg/add.py
example-pkg/subtract.py
example-pkg/extras/__init__.py
example-pkg/extras/divide.py
example-pkg/extras/multiply.py
verysimplemodule/__init__.py
verysimplemodule/add.py
verysimplemodule/subtract.py
verysimplemodule/extras/__init__.py
verysimplemodule/extras/divide.py
verysimplemodule/extras/multiply.py
walgreensbasicmodule/__init__.py
walgreensbasicmodule/add.py
walgreensbasicmodule/subtract.py
walgreensbasicmodule/extras/__init__.py
walgreensbasicmodule/extras/divide.py
walgreensbasicmodule/extras/multiply.py
walgreensmodule/__init__.py
walgreensmodule/add.py
walgreensmodule/subtract.py
walgreensmodule/extras/__init__.py
walgreensmodule/extras/divide.py
walgreensmodule/extras/multiply.py
example_pkg_varun-0.0.1.dist-info/METADATA
example_pkg_varun-0.0.1.dist-info/WHEEL
example_pkg_varun-0.0.1.dist-info/top_level.txt
example_pkg_varun-0.0.1.dist-info/RECORD
